torch_refine_tilt_axis_angle/__init__.py
torch_refine_tilt_axis_angle/py.typed
torch_refine_tilt_axis_angle/refine_tilt_axis_angle.py
torch_refine_tilt_axis_angle-0.0.3.dist-info/METADATA
torch_refine_tilt_axis_angle-0.0.3.dist-info/WHEEL
torch_refine_tilt_axis_angle-0.0.3.dist-info/licenses/LICENSE
torch_refine_tilt_axis_angle-0.0.3.dist-info/RECORD
